{
    "$schema": "https://raw.githubusercontent.com/Monster-Train-2-Modding-Group/Trainworks-Reloaded/refs/heads/main/schemas/base.json",
    "localization_terms": [
        {
            "key": "PurgeCardFromHandKey",
            "texts": {
                "english": "Choose a card to purge.",
                "chinese": "选择一张卡牌进行移除。"
            }
        },
        {
            "key": "PurgeCardFromHandActionKey",
            "texts": {
                "english": "Purge",
                "chinese": "移除"
            }
        }
    ]
}